colorchef/__init__.py
colorchef/colorchef.py
colorchef-0.0.7.dist-info/METADATA
colorchef-0.0.7.dist-info/WHEEL
colorchef-0.0.7.dist-info/top_level.txt
colorchef-0.0.7.dist-info/RECORD
