Metadata-Version: 2.1
Name: colorchef
Version: 0.0.7
Summary: Paint your terminal with beautifull colors.
Home-page: UNKNOWN
Author: Mithilesh Pradhan
Author-email: knowmit@gmail.com
License: UNKNOWN
Keywords: python,first package
Platform: UNKNOWN
Classifier: Development Status :: 3 - Alpha
Classifier: Intended Audience :: Information Technology
Classifier: Programming Language :: Python :: 2
Classifier: Programming Language :: Python :: 3
Classifier: Operating System :: MacOS :: MacOS X
Classifier: Operating System :: Microsoft :: Windows
